{
    "cards": [
        {
            "card": "Karakas",
            "count": 6,
            "%": 8.571428571428571
        },
        {
            "card": "Wasteland",
            "count": 6,
            "%": 8.571428571428571
        },
        {
            "card": "Black Lotus",
            "count": 5,
            "%": 7.142857142857142
        },
        {
            "card": "Inkmoth Nexus",
            "count": 3,
            "%": 4.285714285714286
        },
        {
            "card": "Sazh's Chocobo",
            "count": 3,
            "%": 4.285714285714286
        }
    ],
    "n_rounds_played": 23,
    "n_wins": 1,
    "nemesis": [
        {
            "player": "IMP",
            "score": -6.0,
            "n_matches": 1
        },
        {
            "player": "Sedris",
            "score": -4.8,
            "n_matches": 5
        },
        {
            "player": "Master_of_Desaster",
            "score": -4.695652173913044,
            "n_matches": 23
        },
        {
            "player": "Schniggi",
            "score": -3.923076923076923,
            "n_matches": 13
        },
        {
            "player": "The green one",
            "score": -3.3333333333333335,
            "n_matches": 9
        }
    ],
    "elo": 1472.847104288733,
    "score_average": 30.585356672313196,
    "score_total": 703.4632034632035,
    "elo_list": [
        1600.0,
        1600.0,
        1600.0,
        1600.0,
        1600.0,
        1600.0,
        1600.0,
        1600.0,
        1600.0,
        1600.0,
        1600.0,
        1600.0,
        1600.0,
        1600.0,
        1600.0,
        1600.0,
        1600.0,
        1600.0,
        1600.0,
        1600.0,
        1600.0,
        1600.0,
        1600.0,
        1600.0,
        1600.0,
        1600.0,
        1600.0,
        1600.0,
        1600.0,
        1600.0,
        1600.0,
        1600.0,
        1600.0,
        1600.0,
        1600.0,
        1600.0,
        1600.0,
        1600.0,
        1600.0,
        1600.0,
        1600.0,
        1600.0,
        1600.0,
        1600.0,
        1600.0,
        1600.0,
        1600.0,
        1600.0,
        1600.0,
        1600.0,
        1600.0,
        1600.0,
        1600.0,
        1600.0,
        1600.0,
        1600.0,
        1600.0,
        1600.0,
        1600.0,
        1600.0,
        1600.0,
        1600.0,
        1600.0,
        1600.0,
        1600.0,
        1600.0,
        1600.0,
        1600.0,
        1600.0,
        1600.0,
        1600.0,
        1600.0,
        1600.0,
        1600.0,
        1600.0,
        1600.0,
        1600.0,
        1600.0,
        1600.0,
        1600.0,
        1600.0,
        1600.0,
        1600.0,
        1600.0,
        1600.0,
        1600.0,
        1600.0,
        1600.0,
        1600.0,
        1600.0,
        1600.0,
        1600.0,
        1600.0,
        1600.0,
        1600.0,
        1600.0,
        1600.0,
        1600.0,
        1600.0,
        1600.0,
        1600.0,
        1600.0,
        1600.0,
        1600.0,
        1600.0,
        1600.0,
        1600.0,
        1600.0,
        1600.0,
        1600.0,
        1600.0,
        1600.0,
        1600.0,
        1600.0,
        1600.0,
        1600.0,
        1600.0,
        1600.0,
        1600.0,
        1600.0,
        1600.0,
        1600.0,
        1600.0,
        1600.0,
        1600.0,
        1600.0,
        1576.020262125123,
        1546.5220693117985,
        1512.0073768398534,
        1504.0823539013657,
        1520.2200739944758,
        1544.341621512998,
        1556.50049667729,
        1559.0267331298005,
        1564.4787934352958,
        1563.9252586145078,
        1560.319125732487,
        1543.3006914655548,
        1525.357701501861,
        1552.9149542051357,
        1535.7601593052734,
        1524.7054719914163,
        1508.098712550749,
        1520.8356732295674,
        1510.4283329024533,
        1494.5345975272562,
        1498.0476948946941,
        1497.2773464119662,
        1472.847104288733
    ],
    "badges": []
}